Metadata-Version: 1.0
Name: pantheios
Version: 0.0.0.0
Summary: Pantheios, for Python
Home-page: https://github.com/synesissoftware/Pantheios.Python
Author: Matt Wilson
Author-email: matthew@synesis.com.au
License: BSD-3-Clause
Platform: UNKNOWN
